{
  "date": "20260602",
  "date_display": "2026/6/2（火曜日）",
  "season": "summer",
  "season_jp": "夏",
  "season_weather": "梅雨。じめじめした蒸し暑さ。紫陽花（アジサイ）が咲く。傘が手放せない",
  "casual_outfit": "Blush linen wrap top, pastel floral midi skirt, tan espadrilles, and a woven crossbody bag.",
  "room_wear": "pastel yellow cropped zip-up hoodie and matching wide-leg shorts set",
  "pajamas": "light cotton pajama set in pale pink gingham-check pattern",
  "room_base": "Tokyo 6-tatami one-room apartment. White bed cover, natural wood bed frame. White desk near the window with a MacBook Air M2 in Starlight. Beige lace curtains. White walls with a few postcards pinned. Warm-colored table lamp.",
  "room_clutter": "convenience store bag and receipt on the floor near the desk",
  "room_seasonal": "a small hydrangea (ajisai) in a vase on the windowsill",
  "day_jp": "火曜日",
  "afternoon": {
    "label": "午前ゼミ",
    "scene": "university seminar room, morning session with focused discussion and presentation",
    "story_scene": "campus corridor right after morning seminar, stretching and looking relieved, holding notebook",
    "outfit_type": "casual"
  },
  "evening": {
    "label": "スタバ作業",
    "scene": "at Starbucks, MacBook Air open with a custom seasonal drink beside it",
    "outfit_type": "casual",
    "post_window": [
      14,
      17
    ]
  },
  "reel_post_window": [
    13,
    17
  ],
  "has_reel": true,
  "has_feed": false,
  "feed_type": "none",
  "feed_food_scene": "",
  "feed_post_window": [],
  "story_slots": [
    {
      "id": "morning",
      "label": "朝",
      "emoji": "🌅",
      "outfit_type": "pajamas",
      "no_makeup": true,
      "post_window": [
        7,
        11
      ],
      "scene_hint": "火曜日の朝 — 午前ゼミに向けて準備中"
    },
    {
      "id": "afternoon",
      "label": "昼",
      "emoji": "☀️",
      "outfit_type": "casual",
      "no_makeup": false,
      "post_window": [
        11,
        18
      ],
      "scene_hint": "午前ゼミ — campus corridor right after morning seminar, stretching and looking relieved, holding notebook"
    },
    {
      "id": "evening",
      "label": "夕方",
      "emoji": "🌆",
      "outfit_type": "casual",
      "no_makeup": false,
      "post_window": [
        18,
        22
      ],
      "scene_hint": "スタバ作業 — at Starbucks, MacBook Air open with a custom seasonal drink beside it"
    },
    {
      "id": "night",
      "label": "深夜",
      "emoji": "🌙",
      "outfit_type": "pajamas",
      "no_makeup": true,
      "post_window": [
        22,
        24
      ],
      "scene_hint": "スタバ作業が終わってお疲れ様 — winding down for the night"
    }
  ],
  "face_conceal": "Mirror selfie: smartphone held up covering the lower half of face — only sleepy eyes, messy bangs, and bedhead visible above the phone screen. Screen faintly reflecting the room."
}